{
  "id": "ICE_CAND_0029_v1_required_count_probe",
  "layoutPath": "prototypes/ice_slide_escape/reports/ICE_CAND_0029_v1_triple_debt_d5_revisit_layout.txt",
  "method": "BFS over state plus capped required-event counts; counterexample is a winning path that does not satisfy required minimum counts",
  "maxStates": 5000000,
  "maxDepth": 200,
  "results": [
    {
      "id": "ICE_CAND_0029_v1_base_required_count_A_to_B",
      "start": [0, 7],
      "goal": [0, 1],
      "status": "complete_no_missing_required_win",
      "visited": 19922,
      "satisfyingWins": 1,
      "requirements": [
        { "pattern": "push_ice", "min": 2 },
        { "pattern": "ice_stop_short:d1", "min": 1 },
        { "pattern": "ice_stop_short:d2", "min": 1 },
        { "pattern": "ice_blocks_ice_no_chain_push", "min": 1 }
      ]
    },
    {
      "id": "ICE_CAND_0029_v1_meta_required_count_C_to_D",
      "start": [16, 7],
      "goal": [16, 6],
      "status": "complete_no_missing_required_win",
      "visited": 621673,
      "satisfyingWins": 1,
      "requirements": [
        { "pattern": "push_ice", "min": 3 },
        { "pattern": "ice_pass_through_d5", "min": 1 },
        { "pattern": "slide_restart_after_group", "min": 1 },
        { "pattern": "ice_blocks_ice_no_chain_push", "min": 1 }
      ]
    }
  ]
}

