{
  "prototype": "ice_slide_escape",
  "id": "ICE_EXP_META_2026_07_01_round16_v37_meta_required_core",
  "playerGoal": [
    17,
    1
  ],
  "requiredWinningEvents": [
    "ice_destroy_group_d6_plus",
    "ice_blocks_ice_no_chain_push"
  ],
  "forbiddenWinningEvents": [],
  "forbiddenReachableEvents": [],
  "starts": [
    {
      "playerStart": [
        17,
        7
      ],
      "legalStart": true,
      "solvable": true,
      "cost": 36,
      "inputs": [
        "left",
        "up",
        "up",
        "up",
        "left",
        "down",
        "left",
        "left",
        "up",
        "left",
        "left",
        "up",
        "down",
        "right",
        "down",
        "right",
        "right",
        "right",
        "down",
        "down",
        "left",
        "left",
        "left",
        "left",
        "up",
        "up",
        "up",
        "right",
        "right",
        "right",
        "right",
        "right",
        "up",
        "up",
        "up",
        "right"
      ],
      "returnedEvents": [
        "walk",
        "walk",
        "walk",
        "walk",
        "push_ice",
        "ice_destroy_group_d6_plus:len2",
        "slide_restart_after_group",
        "ice_blocks_ice_no_chain_push",
        "ice_stop_short:d1",
        "walk",
        "walk",
        "push_ice",
        "ice_stop_short:d2",
        "walk",
        "walk",
        "walk",
        "push_ice",
        "ice_stop_short:d1",
        "walk",
        "walk",
        "walk",
        "walk",
        "walk",
        "walk",
        "walk",
        "walk",
        "walk",
        "walk",
        "walk",
        "walk",
        "walk",
        "push_ice",
        "ice_blocks_ice_no_chain_push",
        "ice_stop_short:d2",
        "walk",
        "walk",
        "walk",
        "walk",
        "walk",
        "walk",
        "walk",
        "walk",
        "walk",
        "walk"
      ],
      "returnedRequiredWinningCovered": true,
      "returnedForbiddenWinningHits": [],
      "graphStatus": "complete",
      "reachableStates": 15515,
      "winningStates": 1,
      "initialScc": {
        "states": 72,
        "out": 9,
        "winOut": 3,
        "deadOut": 6,
        "dist": 4
      },
      "solutionScc": {
        "shape": "branching_win_dag",
        "irreversibleSteps": 4,
        "forcedWinPrefix": 0
      },
      "firstStepLegalEvents": [
        "walk"
      ],
      "winningPathMissingRequiredWinning": {
        "checked": true,
        "found": false,
        "exploredStates": 17069,
        "searchStatus": "complete",
        "reason": "no uncovered goal path in complete search"
      },
      "winningPathMissingRequiredOrWithForbiddenWinning": {
        "checked": true,
        "found": false,
        "exploredStates": 17069,
        "searchStatus": "complete",
        "reason": "no uncovered goal path in complete search"
      },
      "reachableEventScan": {
        "status": "complete",
        "reachableStates": 15515,
        "legalTransitions": 42529,
        "eventOnlyIllegalTransitions": 1168,
        "eventCounts": {
          "walk": 41352,
          "push_ice": 1177,
          "ice_destroy_group_d6_plus:len2": 42,
          "slide_restart_after_group": 70,
          "ice_blocks_ice_no_chain_push": 321,
          "ice_stop_short:d1": 457,
          "push_ice_failed": 1168,
          "ice_stop_short:d2": 280,
          "ice_destroyed_d3": 300,
          "ice_rebound_d4": 110,
          "ice_pass_through_d5:len1": 13,
          "ice_boundary_disappear_after_group": 13,
          "ice_pass_through_d5:len3": 10,
          "ice_pass_through_d5:len2": 18,
          "ice_boundary_disappear:d1": 11,
          "ice_boundary_disappear:d2": 3,
          "ice_boundary_disappear:d5": 3
        },
        "forbiddenReachableHits": []
      },
      "machineGate": "pass",
      "machineGateReasons": []
    }
  ]
}
