{
  "prototype": "ice_slide_escape",
  "id": "ICE_CAND_0013_v3_goal8_required_with_d3",
  "playerGoal": [
    8,
    0
  ],
  "requiredEvents": [
    "ice_pass_through_d5",
    "ice_destroy_group_d6_plus",
    "slide_restart_after_group",
    "ice_destroyed_d3"
  ],
  "forbiddenEvents": [],
  "reportEvents": [],
  "starts": [
    {
      "playerStart": [
        5,
        9
      ],
      "legalStart": true,
      "solvable": true,
      "cost": 36,
      "inputs": [
        "right",
        "right",
        "right",
        "right",
        "right",
        "right",
        "up",
        "up",
        "up",
        "up",
        "up",
        "up",
        "left",
        "left",
        "left",
        "left",
        "up",
        "up",
        "left",
        "left",
        "up",
        "left",
        "left",
        "left",
        "left",
        "left",
        "down",
        "right",
        "up",
        "right",
        "right",
        "right",
        "right",
        "right",
        "right",
        "right"
      ],
      "returnedEvents": [
        "walk",
        "walk",
        "walk",
        "walk",
        "walk",
        "walk",
        "push_ice",
        "ice_pass_through_d5:len1",
        "slide_restart_after_group",
        "ice_stop_short:d1",
        "walk",
        "walk",
        "walk",
        "walk",
        "walk",
        "walk",
        "walk",
        "walk",
        "walk",
        "walk",
        "walk",
        "walk",
        "push_ice",
        "ice_blocks_ice_no_chain_push",
        "ice_destroyed_d3",
        "walk",
        "walk",
        "walk",
        "walk",
        "walk",
        "walk",
        "walk",
        "push_ice",
        "ice_destroy_group_d6_plus:len1",
        "slide_restart_after_group",
        "ice_blocks_ice_no_chain_push",
        "ice_stop_short:d2",
        "walk",
        "walk",
        "walk",
        "walk",
        "walk",
        "walk",
        "walk",
        "walk"
      ],
      "returnedRequiredCovered": true,
      "returnedForbiddenHits": [],
      "graphStatus": "complete",
      "reachableStates": 2747,
      "winningStates": 3,
      "initialScc": {
        "states": 112,
        "out": 5,
        "winOut": 3,
        "deadOut": 2,
        "dist": 3
      },
      "solutionScc": {
        "shape": "branching_win_dag",
        "irreversibleSteps": 3,
        "forcedWinPrefix": 0
      },
      "firstStepLegalEvents": [
        "walk"
      ],
      "winningPathMissingRequired": {
        "checked": true,
        "found": true,
        "cost": 38,
        "inputs": [
          "right",
          "right",
          "right",
          "right",
          "right",
          "right",
          "up",
          "up",
          "up",
          "up",
          "up",
          "up",
          "left",
          "left",
          "left",
          "left",
          "left",
          "left",
          "left",
          "up",
          "up",
          "right",
          "up",
          "left",
          "left",
          "left",
          "left",
          "left",
          "down",
          "right",
          "up",
          "right",
          "right",
          "right",
          "right",
          "right",
          "right",
          "right"
        ],
        "events": [
          "walk",
          "walk",
          "walk",
          "walk",
          "walk",
          "walk",
          "push_ice",
          "ice_pass_through_d5:len1",
          "slide_restart_after_group",
          "ice_stop_short:d1",
          "walk",
          "walk",
          "walk",
          "walk",
          "walk",
          "walk",
          "walk",
          "walk",
          "walk",
          "walk",
          "walk",
          "walk",
          "walk",
          "walk",
          "push_ice",
          "ice_stop_short:d2",
          "walk",
          "walk",
          "walk",
          "walk",
          "walk",
          "walk",
          "walk",
          "push_ice",
          "ice_blocks_ice_no_chain_push",
          "ice_pass_through_d5:len2",
          "slide_restart_after_group",
          "ice_blocks_ice_no_chain_push",
          "ice_stop_short:d2",
          "walk",
          "walk",
          "walk",
          "walk",
          "walk",
          "walk",
          "walk",
          "walk"
        ],
        "exploredStates": 3971,
        "searchStatus": "found"
      },
      "winningPathMissingRequiredOrWithForbidden": {
        "checked": true,
        "found": true,
        "cost": 38,
        "inputs": [
          "right",
          "right",
          "right",
          "right",
          "right",
          "right",
          "up",
          "up",
          "up",
          "up",
          "up",
          "up",
          "left",
          "left",
          "left",
          "left",
          "left",
          "left",
          "left",
          "up",
          "up",
          "right",
          "up",
          "left",
          "left",
          "left",
          "left",
          "left",
          "down",
          "right",
          "up",
          "right",
          "right",
          "right",
          "right",
          "right",
          "right",
          "right"
        ],
        "events": [
          "walk",
          "walk",
          "walk",
          "walk",
          "walk",
          "walk",
          "push_ice",
          "ice_pass_through_d5:len1",
          "slide_restart_after_group",
          "ice_stop_short:d1",
          "walk",
          "walk",
          "walk",
          "walk",
          "walk",
          "walk",
          "walk",
          "walk",
          "walk",
          "walk",
          "walk",
          "walk",
          "walk",
          "walk",
          "push_ice",
          "ice_stop_short:d2",
          "walk",
          "walk",
          "walk",
          "walk",
          "walk",
          "walk",
          "walk",
          "push_ice",
          "ice_blocks_ice_no_chain_push",
          "ice_pass_through_d5:len2",
          "slide_restart_after_group",
          "ice_blocks_ice_no_chain_push",
          "ice_stop_short:d2",
          "walk",
          "walk",
          "walk",
          "walk",
          "walk",
          "walk",
          "walk",
          "walk"
        ],
        "exploredStates": 3971,
        "searchStatus": "found"
      },
      "reachableEventScan": {
        "status": "complete",
        "reachableStates": 2747,
        "legalTransitions": 9716,
        "eventOnlyIllegalTransitions": 15,
        "eventCounts": {
          "walk": 9626,
          "push_ice": 90,
          "ice_boundary_disappear:d1": 39,
          "ice_pass_through_d5:len1": 7,
          "slide_restart_after_group": 13,
          "ice_stop_short:d1": 7,
          "ice_boundary_disappear:d11": 7,
          "ice_stop_short:d2": 8,
          "ice_blocks_ice_no_chain_push": 12,
          "ice_destroyed_d3": 10,
          "push_ice_failed": 15,
          "ice_boundary_disappear:d8": 16,
          "ice_pass_through_d5:len2": 3,
          "ice_destroy_group_d6_plus:len1": 3,
          "ice_boundary_disappear:d5": 3
        },
        "reportHits": []
      },
      "machineGate": "fail",
      "machineGateReasons": [
        "存在缺少 required events 的胜利路径"
      ]
    },
    {
      "playerStart": [
        11,
        9
      ],
      "legalStart": true,
      "solvable": true,
      "cost": 30,
      "inputs": [
        "up",
        "up",
        "up",
        "up",
        "up",
        "up",
        "left",
        "left",
        "left",
        "left",
        "up",
        "up",
        "left",
        "left",
        "up",
        "left",
        "left",
        "left",
        "left",
        "left",
        "down",
        "right",
        "up",
        "right",
        "right",
        "right",
        "right",
        "right",
        "right",
        "right"
      ],
      "returnedEvents": [
        "push_ice",
        "ice_pass_through_d5:len1",
        "slide_restart_after_group",
        "ice_stop_short:d1",
        "walk",
        "walk",
        "walk",
        "walk",
        "walk",
        "walk",
        "walk",
        "walk",
        "walk",
        "walk",
        "walk",
        "walk",
        "push_ice",
        "ice_blocks_ice_no_chain_push",
        "ice_destroyed_d3",
        "walk",
        "walk",
        "walk",
        "walk",
        "walk",
        "walk",
        "walk",
        "push_ice",
        "ice_destroy_group_d6_plus:len1",
        "slide_restart_after_group",
        "ice_blocks_ice_no_chain_push",
        "ice_stop_short:d2",
        "walk",
        "walk",
        "walk",
        "walk",
        "walk",
        "walk",
        "walk",
        "walk"
      ],
      "returnedRequiredCovered": true,
      "returnedForbiddenHits": [],
      "graphStatus": "complete",
      "reachableStates": 2747,
      "winningStates": 3,
      "initialScc": {
        "states": 112,
        "out": 5,
        "winOut": 3,
        "deadOut": 2,
        "dist": 3
      },
      "solutionScc": {
        "shape": "branching_win_dag",
        "irreversibleSteps": 3,
        "forcedWinPrefix": 0
      },
      "firstStepLegalEvents": [
        "ice_pass_through_d5:len1",
        "ice_stop_short:d1",
        "push_ice",
        "slide_restart_after_group",
        "walk"
      ],
      "winningPathMissingRequired": {
        "checked": true,
        "found": true,
        "cost": 32,
        "inputs": [
          "up",
          "up",
          "up",
          "up",
          "up",
          "up",
          "left",
          "left",
          "left",
          "left",
          "left",
          "left",
          "left",
          "up",
          "up",
          "right",
          "up",
          "left",
          "left",
          "left",
          "left",
          "left",
          "down",
          "right",
          "up",
          "right",
          "right",
          "right",
          "right",
          "right",
          "right",
          "right"
        ],
        "events": [
          "push_ice",
          "ice_pass_through_d5:len1",
          "slide_restart_after_group",
          "ice_stop_short:d1",
          "walk",
          "walk",
          "walk",
          "walk",
          "walk",
          "walk",
          "walk",
          "walk",
          "walk",
          "walk",
          "walk",
          "walk",
          "walk",
          "walk",
          "push_ice",
          "ice_stop_short:d2",
          "walk",
          "walk",
          "walk",
          "walk",
          "walk",
          "walk",
          "walk",
          "push_ice",
          "ice_blocks_ice_no_chain_push",
          "ice_pass_through_d5:len2",
          "slide_restart_after_group",
          "ice_blocks_ice_no_chain_push",
          "ice_stop_short:d2",
          "walk",
          "walk",
          "walk",
          "walk",
          "walk",
          "walk",
          "walk",
          "walk"
        ],
        "exploredStates": 2960,
        "searchStatus": "found"
      },
      "winningPathMissingRequiredOrWithForbidden": {
        "checked": true,
        "found": true,
        "cost": 32,
        "inputs": [
          "up",
          "up",
          "up",
          "up",
          "up",
          "up",
          "left",
          "left",
          "left",
          "left",
          "left",
          "left",
          "left",
          "up",
          "up",
          "right",
          "up",
          "left",
          "left",
          "left",
          "left",
          "left",
          "down",
          "right",
          "up",
          "right",
          "right",
          "right",
          "right",
          "right",
          "right",
          "right"
        ],
        "events": [
          "push_ice",
          "ice_pass_through_d5:len1",
          "slide_restart_after_group",
          "ice_stop_short:d1",
          "walk",
          "walk",
          "walk",
          "walk",
          "walk",
          "walk",
          "walk",
          "walk",
          "walk",
          "walk",
          "walk",
          "walk",
          "walk",
          "walk",
          "push_ice",
          "ice_stop_short:d2",
          "walk",
          "walk",
          "walk",
          "walk",
          "walk",
          "walk",
          "walk",
          "push_ice",
          "ice_blocks_ice_no_chain_push",
          "ice_pass_through_d5:len2",
          "slide_restart_after_group",
          "ice_blocks_ice_no_chain_push",
          "ice_stop_short:d2",
          "walk",
          "walk",
          "walk",
          "walk",
          "walk",
          "walk",
          "walk",
          "walk"
        ],
        "exploredStates": 2960,
        "searchStatus": "found"
      },
      "reachableEventScan": {
        "status": "complete",
        "reachableStates": 2747,
        "legalTransitions": 9716,
        "eventOnlyIllegalTransitions": 15,
        "eventCounts": {
          "push_ice": 90,
          "ice_pass_through_d5:len1": 7,
          "slide_restart_after_group": 13,
          "ice_stop_short:d1": 7,
          "walk": 9626,
          "ice_boundary_disappear:d1": 39,
          "ice_boundary_disappear:d11": 7,
          "ice_blocks_ice_no_chain_push": 12,
          "ice_destroyed_d3": 10,
          "push_ice_failed": 15,
          "ice_stop_short:d2": 8,
          "ice_boundary_disappear:d8": 16,
          "ice_destroy_group_d6_plus:len1": 3,
          "ice_pass_through_d5:len2": 3,
          "ice_boundary_disappear:d5": 3
        },
        "reportHits": []
      },
      "machineGate": "fail",
      "machineGateReasons": [
        "存在缺少 required events 的胜利路径"
      ]
    },
    {
      "playerStart": [
        0,
        9
      ],
      "legalStart": true,
      "solvable": true,
      "cost": 41,
      "inputs": [
        "right",
        "right",
        "right",
        "right",
        "right",
        "right",
        "right",
        "right",
        "right",
        "right",
        "right",
        "up",
        "up",
        "up",
        "up",
        "up",
        "up",
        "left",
        "left",
        "left",
        "left",
        "up",
        "up",
        "left",
        "left",
        "up",
        "left",
        "left",
        "left",
        "left",
        "left",
        "down",
        "right",
        "up",
        "right",
        "right",
        "right",
        "right",
        "right",
        "right",
        "right"
      ],
      "returnedEvents": [
        "walk",
        "walk",
        "walk",
        "walk",
        "walk",
        "walk",
        "walk",
        "walk",
        "walk",
        "walk",
        "walk",
        "push_ice",
        "ice_pass_through_d5:len1",
        "slide_restart_after_group",
        "ice_stop_short:d1",
        "walk",
        "walk",
        "walk",
        "walk",
        "walk",
        "walk",
        "walk",
        "walk",
        "walk",
        "walk",
        "walk",
        "walk",
        "push_ice",
        "ice_blocks_ice_no_chain_push",
        "ice_destroyed_d3",
        "walk",
        "walk",
        "walk",
        "walk",
        "walk",
        "walk",
        "walk",
        "push_ice",
        "ice_destroy_group_d6_plus:len1",
        "slide_restart_after_group",
        "ice_blocks_ice_no_chain_push",
        "ice_stop_short:d2",
        "walk",
        "walk",
        "walk",
        "walk",
        "walk",
        "walk",
        "walk",
        "walk"
      ],
      "returnedRequiredCovered": true,
      "returnedForbiddenHits": [],
      "graphStatus": "complete",
      "reachableStates": 2747,
      "winningStates": 3,
      "initialScc": {
        "states": 112,
        "out": 5,
        "winOut": 3,
        "deadOut": 2,
        "dist": 3
      },
      "solutionScc": {
        "shape": "branching_win_dag",
        "irreversibleSteps": 3,
        "forcedWinPrefix": 0
      },
      "firstStepLegalEvents": [
        "walk"
      ],
      "winningPathMissingRequired": {
        "checked": true,
        "found": true,
        "cost": 43,
        "inputs": [
          "right",
          "right",
          "right",
          "right",
          "right",
          "right",
          "right",
          "right",
          "right",
          "right",
          "right",
          "up",
          "up",
          "up",
          "up",
          "up",
          "up",
          "left",
          "left",
          "left",
          "left",
          "left",
          "left",
          "left",
          "up",
          "up",
          "right",
          "up",
          "left",
          "left",
          "left",
          "left",
          "left",
          "down",
          "right",
          "up",
          "right",
          "right",
          "right",
          "right",
          "right",
          "right",
          "right"
        ],
        "events": [
          "walk",
          "walk",
          "walk",
          "walk",
          "walk",
          "walk",
          "walk",
          "walk",
          "walk",
          "walk",
          "walk",
          "push_ice",
          "ice_pass_through_d5:len1",
          "slide_restart_after_group",
          "ice_stop_short:d1",
          "walk",
          "walk",
          "walk",
          "walk",
          "walk",
          "walk",
          "walk",
          "walk",
          "walk",
          "walk",
          "walk",
          "walk",
          "walk",
          "walk",
          "push_ice",
          "ice_stop_short:d2",
          "walk",
          "walk",
          "walk",
          "walk",
          "walk",
          "walk",
          "walk",
          "push_ice",
          "ice_blocks_ice_no_chain_push",
          "ice_pass_through_d5:len2",
          "slide_restart_after_group",
          "ice_blocks_ice_no_chain_push",
          "ice_stop_short:d2",
          "walk",
          "walk",
          "walk",
          "walk",
          "walk",
          "walk",
          "walk",
          "walk"
        ],
        "exploredStates": 4090,
        "searchStatus": "found"
      },
      "winningPathMissingRequiredOrWithForbidden": {
        "checked": true,
        "found": true,
        "cost": 43,
        "inputs": [
          "right",
          "right",
          "right",
          "right",
          "right",
          "right",
          "right",
          "right",
          "right",
          "right",
          "right",
          "up",
          "up",
          "up",
          "up",
          "up",
          "up",
          "left",
          "left",
          "left",
          "left",
          "left",
          "left",
          "left",
          "up",
          "up",
          "right",
          "up",
          "left",
          "left",
          "left",
          "left",
          "left",
          "down",
          "right",
          "up",
          "right",
          "right",
          "right",
          "right",
          "right",
          "right",
          "right"
        ],
        "events": [
          "walk",
          "walk",
          "walk",
          "walk",
          "walk",
          "walk",
          "walk",
          "walk",
          "walk",
          "walk",
          "walk",
          "push_ice",
          "ice_pass_through_d5:len1",
          "slide_restart_after_group",
          "ice_stop_short:d1",
          "walk",
          "walk",
          "walk",
          "walk",
          "walk",
          "walk",
          "walk",
          "walk",
          "walk",
          "walk",
          "walk",
          "walk",
          "walk",
          "walk",
          "push_ice",
          "ice_stop_short:d2",
          "walk",
          "walk",
          "walk",
          "walk",
          "walk",
          "walk",
          "walk",
          "push_ice",
          "ice_blocks_ice_no_chain_push",
          "ice_pass_through_d5:len2",
          "slide_restart_after_group",
          "ice_blocks_ice_no_chain_push",
          "ice_stop_short:d2",
          "walk",
          "walk",
          "walk",
          "walk",
          "walk",
          "walk",
          "walk",
          "walk"
        ],
        "exploredStates": 4090,
        "searchStatus": "found"
      },
      "reachableEventScan": {
        "status": "complete",
        "reachableStates": 2747,
        "legalTransitions": 9716,
        "eventOnlyIllegalTransitions": 15,
        "eventCounts": {
          "walk": 9626,
          "push_ice": 90,
          "ice_blocks_ice_no_chain_push": 12,
          "ice_destroyed_d3": 10,
          "ice_boundary_disappear:d1": 39,
          "ice_boundary_disappear:d8": 16,
          "ice_pass_through_d5:len1": 7,
          "slide_restart_after_group": 13,
          "ice_stop_short:d1": 7,
          "ice_stop_short:d2": 8,
          "ice_boundary_disappear:d11": 7,
          "push_ice_failed": 15,
          "ice_boundary_disappear:d5": 3,
          "ice_pass_through_d5:len2": 3,
          "ice_destroy_group_d6_plus:len1": 3
        },
        "reportHits": []
      },
      "machineGate": "fail",
      "machineGateReasons": [
        "存在缺少 required events 的胜利路径"
      ]
    },
    {
      "playerStart": [
        0,
        1
      ],
      "legalStart": true,
      "solvable": true,
      "cost": 49,
      "inputs": [
        "up",
        "right",
        "right",
        "down",
        "right",
        "right",
        "right",
        "right",
        "down",
        "down",
        "down",
        "down",
        "down",
        "down",
        "down",
        "down",
        "right",
        "right",
        "right",
        "right",
        "right",
        "up",
        "up",
        "up",
        "up",
        "up",
        "up",
        "left",
        "left",
        "left",
        "left",
        "left",
        "left",
        "left",
        "up",
        "left",
        "left",
        "left",
        "left",
        "up",
        "right",
        "up",
        "right",
        "right",
        "right",
        "right",
        "right",
        "right",
        "right"
      ],
      "returnedEvents": [
        "walk",
        "walk",
        "walk",
        "walk",
        "walk",
        "walk",
        "push_ice",
        "ice_stop_short:d2",
        "walk",
        "walk",
        "walk",
        "walk",
        "walk",
        "walk",
        "walk",
        "walk",
        "walk",
        "walk",
        "walk",
        "walk",
        "walk",
        "walk",
        "push_ice",
        "ice_pass_through_d5:len1",
        "slide_restart_after_group",
        "ice_stop_short:d1",
        "walk",
        "walk",
        "walk",
        "walk",
        "walk",
        "walk",
        "walk",
        "walk",
        "walk",
        "walk",
        "walk",
        "walk",
        "walk",
        "walk",
        "walk",
        "walk",
        "walk",
        "walk",
        "push_ice",
        "ice_blocks_ice_no_chain_push",
        "ice_pass_through_d5:len2",
        "slide_restart_after_group",
        "ice_blocks_ice_no_chain_push",
        "ice_stop_short:d2",
        "walk",
        "walk",
        "walk",
        "walk",
        "walk",
        "walk",
        "walk",
        "walk"
      ],
      "returnedRequiredCovered": false,
      "returnedForbiddenHits": [],
      "graphStatus": "complete",
      "reachableStates": 2747,
      "winningStates": 3,
      "initialScc": {
        "states": 112,
        "out": 5,
        "winOut": 3,
        "deadOut": 2,
        "dist": 3
      },
      "solutionScc": {
        "shape": "branching_win_dag",
        "irreversibleSteps": 3,
        "forcedWinPrefix": 0
      },
      "firstStepLegalEvents": [
        "ice_blocks_ice_no_chain_push",
        "ice_destroyed_d3",
        "push_ice",
        "walk"
      ],
      "winningPathMissingRequired": {
        "checked": true,
        "found": true,
        "cost": 49,
        "inputs": [
          "up",
          "right",
          "right",
          "down",
          "right",
          "right",
          "right",
          "right",
          "down",
          "down",
          "down",
          "down",
          "down",
          "down",
          "down",
          "down",
          "right",
          "right",
          "right",
          "right",
          "right",
          "up",
          "up",
          "up",
          "up",
          "up",
          "up",
          "left",
          "left",
          "left",
          "left",
          "left",
          "left",
          "left",
          "up",
          "left",
          "left",
          "left",
          "left",
          "up",
          "right",
          "up",
          "right",
          "right",
          "right",
          "right",
          "right",
          "right",
          "right"
        ],
        "events": [
          "walk",
          "walk",
          "walk",
          "walk",
          "walk",
          "walk",
          "push_ice",
          "ice_stop_short:d2",
          "walk",
          "walk",
          "walk",
          "walk",
          "walk",
          "walk",
          "walk",
          "walk",
          "walk",
          "walk",
          "walk",
          "walk",
          "walk",
          "walk",
          "push_ice",
          "ice_pass_through_d5:len1",
          "slide_restart_after_group",
          "ice_stop_short:d1",
          "walk",
          "walk",
          "walk",
          "walk",
          "walk",
          "walk",
          "walk",
          "walk",
          "walk",
          "walk",
          "walk",
          "walk",
          "walk",
          "walk",
          "walk",
          "walk",
          "walk",
          "walk",
          "push_ice",
          "ice_blocks_ice_no_chain_push",
          "ice_pass_through_d5:len2",
          "slide_restart_after_group",
          "ice_blocks_ice_no_chain_push",
          "ice_stop_short:d2",
          "walk",
          "walk",
          "walk",
          "walk",
          "walk",
          "walk",
          "walk",
          "walk"
        ],
        "exploredStates": 4323,
        "searchStatus": "found"
      },
      "winningPathMissingRequiredOrWithForbidden": {
        "checked": true,
        "found": true,
        "cost": 49,
        "inputs": [
          "up",
          "right",
          "right",
          "down",
          "right",
          "right",
          "right",
          "right",
          "down",
          "down",
          "down",
          "down",
          "down",
          "down",
          "down",
          "down",
          "right",
          "right",
          "right",
          "right",
          "right",
          "up",
          "up",
          "up",
          "up",
          "up",
          "up",
          "left",
          "left",
          "left",
          "left",
          "left",
          "left",
          "left",
          "up",
          "left",
          "left",
          "left",
          "left",
          "up",
          "right",
          "up",
          "right",
          "right",
          "right",
          "right",
          "right",
          "right",
          "right"
        ],
        "events": [
          "walk",
          "walk",
          "walk",
          "walk",
          "walk",
          "walk",
          "push_ice",
          "ice_stop_short:d2",
          "walk",
          "walk",
          "walk",
          "walk",
          "walk",
          "walk",
          "walk",
          "walk",
          "walk",
          "walk",
          "walk",
          "walk",
          "walk",
          "walk",
          "push_ice",
          "ice_pass_through_d5:len1",
          "slide_restart_after_group",
          "ice_stop_short:d1",
          "walk",
          "walk",
          "walk",
          "walk",
          "walk",
          "walk",
          "walk",
          "walk",
          "walk",
          "walk",
          "walk",
          "walk",
          "walk",
          "walk",
          "walk",
          "walk",
          "walk",
          "walk",
          "push_ice",
          "ice_blocks_ice_no_chain_push",
          "ice_pass_through_d5:len2",
          "slide_restart_after_group",
          "ice_blocks_ice_no_chain_push",
          "ice_stop_short:d2",
          "walk",
          "walk",
          "walk",
          "walk",
          "walk",
          "walk",
          "walk",
          "walk"
        ],
        "exploredStates": 4323,
        "searchStatus": "found"
      },
      "reachableEventScan": {
        "status": "complete",
        "reachableStates": 2747,
        "legalTransitions": 9716,
        "eventOnlyIllegalTransitions": 15,
        "eventCounts": {
          "walk": 9626,
          "push_ice": 90,
          "ice_blocks_ice_no_chain_push": 12,
          "ice_destroyed_d3": 10,
          "ice_boundary_disappear:d8": 16,
          "ice_boundary_disappear:d1": 39,
          "ice_stop_short:d2": 8,
          "push_ice_failed": 15,
          "ice_boundary_disappear:d5": 3,
          "ice_pass_through_d5:len2": 3,
          "slide_restart_after_group": 13,
          "ice_destroy_group_d6_plus:len1": 3,
          "ice_pass_through_d5:len1": 7,
          "ice_stop_short:d1": 7,
          "ice_boundary_disappear:d11": 7
        },
        "reportHits": []
      },
      "machineGate": "fail",
      "machineGateReasons": [
        "返回解未覆盖全部 required events",
        "存在缺少 required events 的胜利路径"
      ]
    },
    {
      "playerStart": [
        12,
        9
      ],
      "legalStart": true,
      "solvable": true,
      "cost": 31,
      "inputs": [
        "left",
        "up",
        "up",
        "up",
        "up",
        "up",
        "up",
        "left",
        "left",
        "left",
        "left",
        "up",
        "up",
        "left",
        "left",
        "up",
        "left",
        "left",
        "left",
        "left",
        "left",
        "down",
        "right",
        "up",
        "right",
        "right",
        "right",
        "right",
        "right",
        "right",
        "right"
      ],
      "returnedEvents": [
        "walk",
        "push_ice",
        "ice_pass_through_d5:len1",
        "slide_restart_after_group",
        "ice_stop_short:d1",
        "walk",
        "walk",
        "walk",
        "walk",
        "walk",
        "walk",
        "walk",
        "walk",
        "walk",
        "walk",
        "walk",
        "walk",
        "push_ice",
        "ice_blocks_ice_no_chain_push",
        "ice_destroyed_d3",
        "walk",
        "walk",
        "walk",
        "walk",
        "walk",
        "walk",
        "walk",
        "push_ice",
        "ice_destroy_group_d6_plus:len1",
        "slide_restart_after_group",
        "ice_blocks_ice_no_chain_push",
        "ice_stop_short:d2",
        "walk",
        "walk",
        "walk",
        "walk",
        "walk",
        "walk",
        "walk",
        "walk"
      ],
      "returnedRequiredCovered": true,
      "returnedForbiddenHits": [],
      "graphStatus": "complete",
      "reachableStates": 2747,
      "winningStates": 3,
      "initialScc": {
        "states": 112,
        "out": 5,
        "winOut": 3,
        "deadOut": 2,
        "dist": 3
      },
      "solutionScc": {
        "shape": "branching_win_dag",
        "irreversibleSteps": 3,
        "forcedWinPrefix": 0
      },
      "firstStepLegalEvents": [
        "walk"
      ],
      "winningPathMissingRequired": {
        "checked": true,
        "found": true,
        "cost": 33,
        "inputs": [
          "left",
          "up",
          "up",
          "up",
          "up",
          "up",
          "up",
          "left",
          "left",
          "left",
          "left",
          "left",
          "left",
          "left",
          "up",
          "up",
          "right",
          "up",
          "left",
          "left",
          "left",
          "left",
          "left",
          "down",
          "right",
          "up",
          "right",
          "right",
          "right",
          "right",
          "right",
          "right",
          "right"
        ],
        "events": [
          "walk",
          "push_ice",
          "ice_pass_through_d5:len1",
          "slide_restart_after_group",
          "ice_stop_short:d1",
          "walk",
          "walk",
          "walk",
          "walk",
          "walk",
          "walk",
          "walk",
          "walk",
          "walk",
          "walk",
          "walk",
          "walk",
          "walk",
          "walk",
          "push_ice",
          "ice_stop_short:d2",
          "walk",
          "walk",
          "walk",
          "walk",
          "walk",
          "walk",
          "walk",
          "push_ice",
          "ice_blocks_ice_no_chain_push",
          "ice_pass_through_d5:len2",
          "slide_restart_after_group",
          "ice_blocks_ice_no_chain_push",
          "ice_stop_short:d2",
          "walk",
          "walk",
          "walk",
          "walk",
          "walk",
          "walk",
          "walk",
          "walk"
        ],
        "exploredStates": 3266,
        "searchStatus": "found"
      },
      "winningPathMissingRequiredOrWithForbidden": {
        "checked": true,
        "found": true,
        "cost": 33,
        "inputs": [
          "left",
          "up",
          "up",
          "up",
          "up",
          "up",
          "up",
          "left",
          "left",
          "left",
          "left",
          "left",
          "left",
          "left",
          "up",
          "up",
          "right",
          "up",
          "left",
          "left",
          "left",
          "left",
          "left",
          "down",
          "right",
          "up",
          "right",
          "right",
          "right",
          "right",
          "right",
          "right",
          "right"
        ],
        "events": [
          "walk",
          "push_ice",
          "ice_pass_through_d5:len1",
          "slide_restart_after_group",
          "ice_stop_short:d1",
          "walk",
          "walk",
          "walk",
          "walk",
          "walk",
          "walk",
          "walk",
          "walk",
          "walk",
          "walk",
          "walk",
          "walk",
          "walk",
          "walk",
          "push_ice",
          "ice_stop_short:d2",
          "walk",
          "walk",
          "walk",
          "walk",
          "walk",
          "walk",
          "walk",
          "push_ice",
          "ice_blocks_ice_no_chain_push",
          "ice_pass_through_d5:len2",
          "slide_restart_after_group",
          "ice_blocks_ice_no_chain_push",
          "ice_stop_short:d2",
          "walk",
          "walk",
          "walk",
          "walk",
          "walk",
          "walk",
          "walk",
          "walk"
        ],
        "exploredStates": 3266,
        "searchStatus": "found"
      },
      "reachableEventScan": {
        "status": "complete",
        "reachableStates": 2747,
        "legalTransitions": 9716,
        "eventOnlyIllegalTransitions": 15,
        "eventCounts": {
          "walk": 9626,
          "push_ice": 90,
          "ice_boundary_disappear:d11": 7,
          "ice_pass_through_d5:len1": 7,
          "slide_restart_after_group": 13,
          "ice_stop_short:d1": 7,
          "ice_boundary_disappear:d1": 39,
          "ice_blocks_ice_no_chain_push": 12,
          "ice_destroyed_d3": 10,
          "push_ice_failed": 15,
          "ice_stop_short:d2": 8,
          "ice_boundary_disappear:d8": 16,
          "ice_destroy_group_d6_plus:len1": 3,
          "ice_pass_through_d5:len2": 3,
          "ice_boundary_disappear:d5": 3
        },
        "reportHits": []
      },
      "machineGate": "fail",
      "machineGateReasons": [
        "存在缺少 required events 的胜利路径"
      ]
    }
  ]
}
