{
  "prototype": "ice_slide_escape",
  "id": "ICE_CAND_0012_meta_split_top_pocket_meta",
  "playerGoal": [
    0,
    7
  ],
  "requiredEvents": [
    "ice_destroy_group_d6_plus",
    "ice_rebound_d4",
    "ice_pass_through_d5",
    "slide_restart_after_group"
  ],
  "forbiddenEvents": [],
  "reportEvents": [],
  "starts": [
    {
      "playerStart": [
        6,
        0
      ],
      "legalStart": true,
      "solvable": false,
      "inputs": [],
      "returnedEvents": [],
      "returnedRequiredCovered": false,
      "returnedForbiddenHits": [],
      "graphStatus": "complete",
      "reachableStates": 412,
      "winningStates": 0,
      "initialScc": {
        "states": 2,
        "out": 1,
        "winOut": 0,
        "deadOut": 1,
        "dist": null
      },
      "solutionScc": {
        "shape": "no_win_path",
        "irreversibleSteps": 0,
        "forcedWinPrefix": 0
      },
      "firstStepLegalEvents": [
        "walk"
      ],
      "winningPathMissingRequired": {
        "checked": true,
        "found": false,
        "exploredStates": 412,
        "searchStatus": "complete",
        "reason": "no uncovered goal path in complete search"
      },
      "winningPathMissingRequiredOrWithForbidden": {
        "checked": true,
        "found": false,
        "exploredStates": 412,
        "searchStatus": "complete",
        "reason": "no uncovered goal path in complete search"
      },
      "reachableEventScan": {
        "status": "complete",
        "reachableStates": 412,
        "legalTransitions": 946,
        "eventOnlyIllegalTransitions": 6,
        "eventCounts": {
          "walk": 932,
          "push_ice": 14,
          "ice_destroy_group_d6_plus:len1": 1,
          "ice_boundary_disappear_after_group": 2,
          "ice_destroy_group_d6_plus:len3": 1,
          "ice_boundary_disappear:d1": 8,
          "ice_stop_short:d1": 2,
          "push_ice_failed": 6,
          "ice_stop_short:d2": 2
        },
        "reportHits": []
      },
      "machineGate": "fail",
      "machineGateReasons": [
        "该显式起终点不可解"
      ]
    }
  ]
}
