{
  "prototype": "ice_slide_escape",
  "id": "ICE_CAND_0006_meta_top_to_left",
  "playerGoal": [
    0,
    3
  ],
  "requiredEvents": [
    "ice_rebound_d4",
    "ice_pass_through_d5",
    "ice_destroy_group_d6_plus",
    "slide_restart_after_group"
  ],
  "forbiddenEvents": [],
  "reportEvents": [],
  "starts": [
    {
      "playerStart": [
        9,
        0
      ],
      "legalStart": true,
      "solvable": false,
      "inputs": [],
      "returnedEvents": [],
      "returnedRequiredCovered": false,
      "returnedForbiddenHits": [],
      "graphStatus": "complete",
      "reachableStates": 15,
      "winningStates": 0,
      "initialScc": {
        "states": 7,
        "out": 1,
        "winOut": 0,
        "deadOut": 1,
        "dist": null
      },
      "solutionScc": {
        "shape": "no_win_path",
        "irreversibleSteps": 0,
        "forcedWinPrefix": 0
      },
      "firstStepLegalEvents": [
        "walk"
      ],
      "winningPathMissingRequired": {
        "checked": true,
        "found": false,
        "exploredStates": 15,
        "searchStatus": "complete",
        "reason": "no uncovered goal path in complete search"
      },
      "winningPathMissingRequiredOrWithForbidden": {
        "checked": true,
        "found": false,
        "exploredStates": 15,
        "searchStatus": "complete",
        "reason": "no uncovered goal path in complete search"
      },
      "reachableEventScan": {
        "status": "complete",
        "reachableStates": 15,
        "legalTransitions": 31,
        "eventOnlyIllegalTransitions": 1,
        "eventCounts": {
          "walk": 30,
          "push_ice": 1,
          "ice_stop_short:d1": 1,
          "push_ice_failed": 1
        },
        "reportHits": []
      },
      "machineGate": "fail",
      "machineGateReasons": [
        "该显式起终点不可解"
      ]
    }
  ]
}
